hubmap_pipeline_release_mgmt/__init__.py
hubmap_pipeline_release_mgmt/config_default.yaml
hubmap_pipeline_release_mgmt/tag_release_pipeline.py
hubmap_pipeline_release_mgmt-0.6.2.dist-info/LICENSE
hubmap_pipeline_release_mgmt-0.6.2.dist-info/METADATA
hubmap_pipeline_release_mgmt-0.6.2.dist-info/WHEEL
hubmap_pipeline_release_mgmt-0.6.2.dist-info/entry_points.txt
hubmap_pipeline_release_mgmt-0.6.2.dist-info/top_level.txt
hubmap_pipeline_release_mgmt-0.6.2.dist-info/RECORD
