Metadata-Version: 2.1
Name: hubmap-pipeline-release-mgmt
Version: 0.6.2
Summary: Management scripts for releasing HuBMAP computational pipelines
Home-page: https://github.com/hubmapconsortium/pipeline-release-mgmt
Author: Matt Ruffalo
Author-email: mruffalo@cs.cmu.edu
License: MIT
Keywords: docker automation
Classifier: Development Status :: 4 - Beta
Classifier: Intended Audience :: Developers
Classifier: Topic :: Software Development
Classifier: License :: OSI Approved :: MIT License
Classifier: Programming Language :: Python :: 3 :: Only
Classifier: Programming Language :: Python :: 3.6
Classifier: Programming Language :: Python :: 3.7
Classifier: Programming Language :: Python :: 3.8
Classifier: Programming Language :: Python :: 3.9
Classifier: Programming Language :: Python :: 3.10
Requires-Python: >=3.6
License-File: LICENSE
Requires-Dist: confuse
Requires-Dist: multi-docker-build >=0.7.1
